tailwindall/__init__.py
tailwindall/bases.py
tailwindall/classes_lib/classes.py
tailwindall/fonts.py
tailwindall/graphics_lib/events.py
tailwindall/graphics_lib/examples/parkour.py
tailwindall/graphics_lib/fonts/FreeSansBold.ttf
tailwindall/graphics_lib/graphics.py
tailwindall/graphics_lib/objects.py
tailwindall/graphics_lib/scenes.py
tailwindall/graphing.py
tailwindall/logger.py
tailwindall/main.py
tailwindall/maths_lib/angles.py
tailwindall/maths_lib/lines.py
tailwindall/maths_lib/physics.py
tailwindall/maths_lib/shapes.py
tailwindall/nerd_fonts/FiraCodeNerdFont-Bold.ttf
tailwindall/nerd_fonts/FiraCodeNerdFont-Light.ttf
tailwindall/nerd_fonts/FiraCodeNerdFont-Medium.ttf
tailwindall/nerd_fonts/FiraCodeNerdFont-Regular.ttf
tailwindall/nerd_fonts/FiraCodeNerdFont-Retina.ttf
tailwindall/nerd_fonts/FiraCodeNerdFont-SemiBold.ttf
tailwindall/nerd_fonts/FiraCodeNerdFontMono-Bold.ttf
tailwindall/nerd_fonts/FiraCodeNerdFontMono-Light.ttf
tailwindall/nerd_fonts/FiraCodeNerdFontMono-Medium.ttf
tailwindall/nerd_fonts/FiraCodeNerdFontMono-Regular.ttf
tailwindall/nerd_fonts/FiraCodeNerdFontMono-Retina.ttf
tailwindall/nerd_fonts/FiraCodeNerdFontMono-SemiBold.ttf
tailwindall/nerd_fonts/FiraCodeNerdFontPropo-Bold.ttf
tailwindall/nerd_fonts/FiraCodeNerdFontPropo-Light.ttf
tailwindall/nerd_fonts/FiraCodeNerdFontPropo-Medium.ttf
tailwindall/nerd_fonts/FiraCodeNerdFontPropo-Regular.ttf
tailwindall/nerd_fonts/FiraCodeNerdFontPropo-Retina.ttf
tailwindall/nerd_fonts/FiraCodeNerdFontPropo-SemiBold.ttf
tailwindall/network_lib/client.py
tailwindall/network_lib/database.py
tailwindall/network_lib/network.py
tailwindall/network_lib/server.py
tailwindall/popup.py
tailwindall/statistics_lib/diagrams.py
tailwindall/statistics_lib/statistics.py
tailwindall/styles.py
tailwindall/util.py
tailwindall/web_lib/components.py
tailwindall/web_lib/js.py
tailwindall/web_lib/tw.py
tailwindall/web_lib/web.py
tailwindall/widget.py
tailwindall/widgets.py
tailwindall/window.py
tailwindall-0.3.4.dist-info/METADATA
tailwindall-0.3.4.dist-info/WHEEL
tailwindall-0.3.4.dist-info/RECORD
