Metadata-Version: 2.1
Name: tailwindall
Version: 0.3.4
Summary: An all in one library for python
License: MIT
Author: Paul Hodges
Author-email: paul.hodges@student.education.wa.edu.au
Requires-Python: >=3.11,<4.0
Classifier: License :: OSI Approved :: MIT License
Classifier: Programming Language :: Python :: 3
Classifier: Programming Language :: Python :: 3.11
Classifier: Programming Language :: Python :: 3.12
Requires-Dist: Flask (>=2.0.2,<3.0.0)
Requires-Dist: Pillow (>=10.0.0,<11.0.0)
Requires-Dist: customtkinter (>=5.2.0,<6.0.0)
Requires-Dist: matplotlib (>=3.7.3,<4.0.0)
Requires-Dist: nerdfonts (>=1.0.0,<2.0.0)
Requires-Dist: numpy (>=1.21.2,<2.0.0)
Requires-Dist: pygame (>=2.5.1,<3.0.0)
Requires-Dist: pyglet (>=1.5.21,<2.0.0)
Requires-Dist: screeninfo (>=0.8.1,<0.9.0)
Requires-Dist: twine (>=3.4.2,<4.0.0)
